Metadata-Version: 1.1
Name: k8s-build-maps
Version: 0.0.7
Summary: Build a directory of Kubernetes ConfigMap/Secret manifests, inserting data from files.
Home-page: https://github.com/nathforge/k8s-build-maps
Author: Nathan Reynolds
Author-email: email@nreynolds.co.uk
License: UNKNOWN
Platform: UNKNOWN
Classifier: Development Status :: 4 - Beta
Classifier: Intended Audience :: Developers
Classifier: Topic :: Software Development
Classifier: License :: OSI Approved :: MIT License
Classifier: Programming Language :: Python :: 2
Classifier: Programming Language :: Python :: 2.7
Classifier: Programming Language :: Python :: 3
Classifier: Programming Language :: Python :: 3.6
